{
  "generated_at": "2026-04-06T05:55:48.558524Z",
  "top_insights": [
    "I have a friend who used to work for 2 billionaires after all he's seen",
    "Normalize not having an opinion on things you don’t understand",
    "I’ve never told this story before publicly but, I used to be a journalist covering",
    "Go on more walks",
    "All of X making sure the map doesn’t flip to blue when our eyes close…"
  ],
  "hook_patterns": [
    "insight",
    "contrarian"
  ],
  "angles": [
    "I have a friend who used to work for 2 billionaires after all he's seen he said to me, \"I wish you not one penny over $299 million",
    "Normalize not having an opinion on things you don’t understand",
    "I’ve never told this story before publicly but, I used to be a journalist covering human trafficking on the US Mexico border"
  ],
  "emotional_drivers": [
    "validation",
    "ambition"
  ],
  "emerging_narrative": "I have a friend who used to work for 2 billionaires after all he's seen he said to me, \"I wish you not one penny over $299 million",
  "viral_examples": [
    {
      "tweet_id": "1939089188441219258",
      "author": "Codie_Sanchez",
      "text": "I have a friend who used to work for 2 billionaires after all he's seen he said to me, \"I wish you not one penny over $299 million. Reality gets completely lost somewhere after that.\" I think about that sometimes.",
      "likes": 194000,
      "replies": 1300,
      "retweets": 11000,
      "rank_score": 54975.0,
      "timestamp": "2025-06-28T00:00:00Z",
      "source": "creator"
    },
    {
      "tweet_id": "1609189890398232582",
      "author": "thedankoe",
      "text": "Normalize not having an opinion on things you don’t understand.",
      "likes": 55000,
      "replies": 464,
      "retweets": 14000,
      "rank_score": 21098.0,
      "timestamp": "2022-12-31T00:00:00Z",
      "source": "creator"
    },
    {
      "tweet_id": "1855971337476477418",
      "author": "Codie_Sanchez",
      "text": "I’ve never told this story before publicly but, I used to be a journalist covering human trafficking on the US Mexico border. I’ve crossed the border illegally covering migrants and cartels countless times. I saw young women in the morgue after they were raped and brutalized in Show more",
      "likes": 53000,
      "replies": 940,
      "retweets": 12000,
      "rank_score": 19955.0,
      "timestamp": "2024-11-11T00:00:00Z",
      "source": "creator"
    },
    {
      "tweet_id": "1860673473749909984",
      "author": "thedankoe",
      "text": "Go on more walks. Walk for no reason. Walk to solve a problem. Walk to blow off steam. Walk to get outside. Walk to listen, read, and learn. Walk to escape distractions. Walk to improve your health. Walk to think. A simple walking habit can change absolutely everything.",
      "likes": 56000,
      "replies": 496,
      "retweets": 11000,
      "rank_score": 19872.0,
      "timestamp": "2024-11-24T00:00:00Z",
      "source": "creator"
    },
    {
      "tweet_id": "1854018384301572571",
      "author": "Codie_Sanchez",
      "text": "All of X making sure the map doesn’t flip to blue when our eyes close…",
      "likes": 59000,
      "replies": 637,
      "retweets": 4700,
      "rank_score": 17577.75,
      "timestamp": "2024-11-06T00:00:00Z",
      "source": "creator"
    }
  ],
  "analyses_count": 20,
  "winning_patterns": [
    "insight",
    "contrarian"
  ],
  "failed_patterns": [],
  "avoid_recent_hooks": [
    "Most people chase money. The ultra-wealthy chase silence.",
    "The biggest lie in the creator economy is that you need a strategy.",
    "Institutions monetize access. Creators monetize math.",
    "I have a friend who worked for 2 billionaires. After seeing the private jets and the stress, he told",
    "The most expensive thing you own is your attention."
  ],
  "avoid_recent_ideas": [
    "Most people chase money. The ultra-wealthy chase silence. We are taught to equate noise with progress. More meetings, more news, more optimi",
    "The biggest lie in the creator economy is that you need a strategy.\n\nStrategies are for people waiting for permission.\n\nSelf-reliance is for",
    "Institutions monetize access. Creators monetize math.\n\nOne requires permission. The other requires proof.\n\nHere is the 4-step shift from emp",
    "I have a friend who worked for 2 billionaires. After seeing the private jets and the stress, he told me:\n\n\"I wish you never make a penny ove",
    "The most expensive thing you own is your attention.\n\nYet 99% of creators trade it for free. They give away their best ideas in threads, tips"
  ],
  "source_summary": {
    "creator": 20
  }
}